cosmodata/__init__.py
cosmodata/base.py
cosmodata/graph_gen.py
cosmodata/py_configs.py
cosmodata/util.py
cosmodata-0.0.5.dist-info/licenses/LICENSE
cosmodata-0.0.5.dist-info/METADATA
cosmodata-0.0.5.dist-info/WHEEL
cosmodata-0.0.5.dist-info/top_level.txt
cosmodata-0.0.5.dist-info/RECORD
