Metadata-Version: 2.4
Name: cosmodata
Version: 0.0.5
Summary: A portal to data sources
Home-page: https://github.com/cosmograph-org/cosmodata/
License: mit
Platform: any
License-File: LICENSE
Requires-Dist: pandas
Requires-Dist: graze
Requires-Dist: tabled
Requires-Dist: linked
Provides-Extra: testing
Dynamic: license-file
